{
  "meta": {
    "version": "1.0.0",
    "lastUpdated": "2024-12-28",
    "totalNodes": 58,
    "subjects": [
      "歯周病学",
      "衛生・公衆衛生・医療管理",
      "微生物・免疫・薬理・歯科理工"
    ]
  },
  "nodes": [
    {
      "id": "EISEI_001",
      "subject": "衛生・公衆衛生・医療管理",
      "level": 1,
      "parentId": null,
      "title": "歯科保健医療総論Ⅰ（保健医療論）",
      "path": "衛生・公衆衛生・医療管理＞歯科保健医療総論Ⅰ（保健医療論）",
      "order": 1,
      "synonyms": "保健医療論",
      "keywords": "",
      "priority": 2,
      "source": "ANSWER 2023 vol.4"
    },
    {
      "id": "EISEI_001_01",
      "subject": "衛生・公衆衛生・医療管理",
      "level": 2,
      "parentId": "EISEI_001",
      "title": "健康・疾病・障害の概念",
      "path": "衛生・公衆衛生・医療管理＞歯科保健医療総論Ⅰ＞健康・疾病・障害の概念",
      "order": 1,
      "synonyms": "",
      "keywords": "健康の定義/QOL/ICF",
      "priority": 2,
      "source": "ANSWER 2023 vol.4"
    },
    {
      "id": "EISEI_001_02",
      "subject": "衛生・公衆衛生・医療管理",
      "level": 2,
      "parentId": "EISEI_001",
      "title": "保健・医療・福祉・介護関係法規",
      "path": "衛生・公衆衛生・医療管理＞歯科保健医療総論Ⅰ＞保健・医療・福祉・介護関係法規",
      "order": 2,
      "synonyms": "",
      "keywords": "医療法/歯科医師法/健康増進法",
      "priority": 2,
      "source": "ANSWER 2023 vol.4"
    },
    {
      "id": "EISEI_001_03",
      "subject": "衛生・公衆衛生・医療管理",
      "level": 2,
      "parentId": "EISEI_001",
      "title": "保健・医療・福祉・介護の仕組みと資源",
      "path": "衛生・公衆衛生・医療管理＞歯科保健医療総論Ⅰ＞保健・医療・福祉・介護の仕組みと資源",
      "order": 3,
      "synonyms": "",
      "keywords": "医療保険/介護保険",
      "priority": 2,
      "source": "ANSWER 2023 vol.4"
    },
    {
      "id": "EISEI_001_04",
      "subject": "衛生・公衆衛生・医療管理",
      "level": 2,
      "parentId": "EISEI_001",
      "title": "地域保健, 地域医療",
      "path": "衛生・公衆衛生・医療管理＞歯科保健医療総論Ⅰ＞地域保健, 地域医療",
      "order": 4,
      "synonyms": "",
      "keywords": "保健所/市町村保健センター",
      "priority": 2,
      "source": "ANSWER 2023 vol.4"
    },
    {
      "id": "EISEI_001_05",
      "subject": "衛生・公衆衛生・医療管理",
      "level": 2,
      "parentId": "EISEI_001",
      "title": "歯科法医学",
      "path": "衛生・公衆衛生・医療管理＞歯科保健医療総論Ⅰ＞歯科法医学",
      "order": 5,
      "synonyms": "",
      "keywords": "個人識別/死後変化",
      "priority": 2,
      "source": "ANSWER 2023 vol.4"
    },
    {
      "id": "EISEI_001_06",
      "subject": "衛生・公衆衛生・医療管理",
      "level": 2,
      "parentId": "EISEI_001",
      "title": "社会保障と医療経済",
      "path": "衛生・公衆衛生・医療管理＞歯科保健医療総論Ⅰ＞社会保障と医療経済",
      "order": 6,
      "synonyms": "",
      "keywords": "国民医療費/診療報酬",
      "priority": 2,
      "source": "ANSWER 2023 vol.4"
    },
    {
      "id": "EISEI_001_07",
      "subject": "衛生・公衆衛生・医療管理",
      "level": 2,
      "parentId": "EISEI_001",
      "title": "国際保健",
      "path": "衛生・公衆衛生・医療管理＞歯科保健医療総論Ⅰ＞国際保健",
      "order": 7,
      "synonyms": "",
      "keywords": "WHO/SDGs",
      "priority": 2,
      "source": "ANSWER 2023 vol.4"
    },
    {
      "id": "EISEI_002",
      "subject": "衛生・公衆衛生・医療管理",
      "level": 1,
      "parentId": null,
      "title": "歯科保健医療総論Ⅱ（健康管理・増進と予防）",
      "path": "衛生・公衆衛生・医療管理＞歯科保健医療総論Ⅱ（健康管理・増進と予防）",
      "order": 2,
      "synonyms": "健康管理・増進と予防",
      "keywords": "",
      "priority": 2,
      "source": "ANSWER 2023 vol.4"
    },
    {
      "id": "EISEI_002_01",
      "subject": "衛生・公衆衛生・医療管理",
      "level": 2,
      "parentId": "EISEI_002",
      "title": "健康の保持・増進と予防",
      "path": "衛生・公衆衛生・医療管理＞歯科保健医療総論Ⅱ＞健康の保持・増進と予防",
      "order": 1,
      "synonyms": "",
      "keywords": "一次予防/二次予防/三次予防",
      "priority": 2,
      "source": "ANSWER 2023 vol.4"
    },
    {
      "id": "EISEI_002_02",
      "subject": "衛生・公衆衛生・医療管理",
      "level": 2,
      "parentId": "EISEI_002",
      "title": "母子保健, 母子歯科保健",
      "path": "衛生・公衆衛生・医療管理＞歯科保健医療総論Ⅱ＞母子保健, 母子歯科保健",
      "order": 2,
      "synonyms": "",
      "keywords": "母子健康手帳/乳幼児健診",
      "priority": 2,
      "source": "ANSWER 2023 vol.4"
    },
    {
      "id": "EISEI_002_03",
      "subject": "衛生・公衆衛生・医療管理",
      "level": 2,
      "parentId": "EISEI_002",
      "title": "学校保健, 学校安全, 学校歯科保健",
      "path": "衛生・公衆衛生・医療管理＞歯科保健医療総論Ⅱ＞学校保健, 学校安全, 学校歯科保健",
      "order": 3,
      "synonyms": "",
      "keywords": "学校歯科健診/COG",
      "priority": 2,
      "source": "ANSWER 2023 vol.4"
    },
    {
      "id": "EISEI_002_04",
      "subject": "衛生・公衆衛生・医療管理",
      "level": 2,
      "parentId": "EISEI_002",
      "title": "産業保健, 産業歯科保健",
      "path": "衛生・公衆衛生・医療管理＞歯科保健医療総論Ⅱ＞産業保健, 産業歯科保健",
      "order": 4,
      "synonyms": "",
      "keywords": "労働安全衛生法/特殊健診",
      "priority": 2,
      "source": "ANSWER 2023 vol.4"
    },
    {
      "id": "EISEI_002_05",
      "subject": "衛生・公衆衛生・医療管理",
      "level": 2,
      "parentId": "EISEI_002",
      "title": "成人保健, 成人歯科保健",
      "path": "衛生・公衆衛生・医療管理＞歯科保健医療総論Ⅱ＞成人保健, 成人歯科保健",
      "order": 5,
      "synonyms": "",
      "keywords": "特定健診/歯周疾患検診",
      "priority": 2,
      "source": "ANSWER 2023 vol.4"
    },
    {
      "id": "EISEI_002_06",
      "subject": "衛生・公衆衛生・医療管理",
      "level": 2,
      "parentId": "EISEI_002",
      "title": "高齢者保健",
      "path": "衛生・公衆衛生・医療管理＞歯科保健医療総論Ⅱ＞高齢者保健",
      "order": 6,
      "synonyms": "",
      "keywords": "後期高齢者医療/介護予防",
      "priority": 2,
      "source": "ANSWER 2023 vol.4"
    },
    {
      "id": "EISEI_002_07",
      "subject": "衛生・公衆衛生・医療管理",
      "level": 2,
      "parentId": "EISEI_002",
      "title": "障害者保健福祉",
      "path": "衛生・公衆衛生・医療管理＞歯科保健医療総論Ⅱ＞障害者保健福祉",
      "order": 7,
      "synonyms": "",
      "keywords": "障害者総合支援法",
      "priority": 2,
      "source": "ANSWER 2023 vol.4"
    },
    {
      "id": "EISEI_002_08",
      "subject": "衛生・公衆衛生・医療管理",
      "level": 2,
      "parentId": "EISEI_002",
      "title": "人口統計と保健統計",
      "path": "衛生・公衆衛生・医療管理＞歯科保健医療総論Ⅱ＞人口統計と保健統計",
      "order": 8,
      "synonyms": "",
      "keywords": "人口動態統計/歯科疾患実態調査",
      "priority": 2,
      "source": "ANSWER 2023 vol.4"
    },
    {
      "id": "EISEI_002_09",
      "subject": "衛生・公衆衛生・医療管理",
      "level": 2,
      "parentId": "EISEI_002",
      "title": "疫学とその応用",
      "path": "衛生・公衆衛生・医療管理＞歯科保健医療総論Ⅱ＞疫学とその応用",
      "order": 9,
      "synonyms": "",
      "keywords": "オッズ比/相対危険/罹患率/有病率",
      "priority": 2,
      "source": "ANSWER 2023 vol.4"
    },
    {
      "id": "EISEI_002_10",
      "subject": "衛生・公衆衛生・医療管理",
      "level": 2,
      "parentId": "EISEI_002",
      "title": "感染症対策",
      "path": "衛生・公衆衛生・医療管理＞歯科保健医療総論Ⅱ＞感染症対策",
      "order": 10,
      "synonyms": "",
      "keywords": "標準予防策/感染症法",
      "priority": 2,
      "source": "ANSWER 2023 vol.4"
    },
    {
      "id": "EISEI_002_11",
      "subject": "衛生・公衆衛生・医療管理",
      "level": 2,
      "parentId": "EISEI_002",
      "title": "国民栄養と食品保健",
      "path": "衛生・公衆衛生・医療管理＞歯科保健医療総論Ⅱ＞国民栄養と食品保健",
      "order": 11,
      "synonyms": "",
      "keywords": "食事摂取基準/食品衛生",
      "priority": 2,
      "source": "ANSWER 2023 vol.4"
    },
    {
      "id": "EISEI_002_12",
      "subject": "衛生・公衆衛生・医療管理",
      "level": 2,
      "parentId": "EISEI_002",
      "title": "環境保健",
      "path": "衛生・公衆衛生・医療管理＞歯科保健医療総論Ⅱ＞環境保健",
      "order": 12,
      "synonyms": "",
      "keywords": "環境基本法/公害",
      "priority": 2,
      "source": "ANSWER 2023 vol.4"
    },
    {
      "id": "EISEI_003",
      "subject": "衛生・公衆衛生・医療管理",
      "level": 1,
      "parentId": null,
      "title": "歯科疾患の予防・管理",
      "path": "衛生・公衆衛生・医療管理＞歯科疾患の予防・管理",
      "order": 3,
      "synonyms": "",
      "keywords": "",
      "priority": 2,
      "source": "ANSWER 2023 vol.4"
    },
    {
      "id": "EISEI_003_01",
      "subject": "衛生・公衆衛生・医療管理",
      "level": 2,
      "parentId": "EISEI_003",
      "title": "齲蝕の予防・管理",
      "path": "衛生・公衆衛生・医療管理＞歯科疾患の予防・管理＞齲蝕の予防・管理",
      "order": 1,
      "synonyms": "",
      "keywords": "フッ化物/シーラント/代用甘味料",
      "priority": 2,
      "source": "ANSWER 2023 vol.4"
    },
    {
      "id": "EISEI_003_02",
      "subject": "衛生・公衆衛生・医療管理",
      "level": 2,
      "parentId": "EISEI_003",
      "title": "歯周病の予防・管理",
      "path": "衛生・公衆衛生・医療管理＞歯科疾患の予防・管理＞歯周病の予防・管理",
      "order": 2,
      "synonyms": "",
      "keywords": "プラークコントロール/PMTC",
      "priority": 2,
      "source": "ANSWER 2023 vol.4"
    },
    {
      "id": "EISEI_003_03",
      "subject": "衛生・公衆衛生・医療管理",
      "level": 2,
      "parentId": "EISEI_003",
      "title": "不正咬合の予防・管理",
      "path": "衛生・公衆衛生・医療管理＞歯科疾患の予防・管理＞不正咬合の予防・管理",
      "order": 3,
      "synonyms": "",
      "keywords": "口腔習癖",
      "priority": 2,
      "source": "ANSWER 2023 vol.4"
    },
    {
      "id": "EISEI_003_04",
      "subject": "衛生・公衆衛生・医療管理",
      "level": 2,
      "parentId": "EISEI_003",
      "title": "口臭の予防・管理",
      "path": "衛生・公衆衛生・医療管理＞歯科疾患の予防・管理＞口臭の予防・管理",
      "order": 4,
      "synonyms": "",
      "keywords": "VSC/舌苔",
      "priority": 2,
      "source": "ANSWER 2023 vol.4"
    },
    {
      "id": "EISEI_003_05",
      "subject": "衛生・公衆衛生・医療管理",
      "level": 2,
      "parentId": "EISEI_003",
      "title": "その他の疾患の予防・管理",
      "path": "衛生・公衆衛生・医療管理＞歯科疾患の予防・管理＞その他の疾患の予防・管理",
      "order": 5,
      "synonyms": "",
      "keywords": "口腔乾燥/歯の外傷",
      "priority": 2,
      "source": "ANSWER 2023 vol.4"
    },
    {
      "id": "EISEI_003_06",
      "subject": "衛生・公衆衛生・医療管理",
      "level": 2,
      "parentId": "EISEI_003",
      "title": "保健指導",
      "path": "衛生・公衆衛生・医療管理＞歯科疾患の予防・管理＞保健指導",
      "order": 6,
      "synonyms": "",
      "keywords": "動機づけ/行動変容",
      "priority": 2,
      "source": "ANSWER 2023 vol.4"
    },
    {
      "id": "EISEI_004",
      "subject": "衛生・公衆衛生・医療管理",
      "level": 1,
      "parentId": null,
      "title": "必修の基本的事項",
      "path": "衛生・公衆衛生・医療管理＞必修の基本的事項",
      "order": 4,
      "synonyms": "",
      "keywords": "",
      "priority": 1,
      "source": "ANSWER 2023 vol.4"
    },
    {
      "id": "EISEI_004_01",
      "subject": "衛生・公衆衛生・医療管理",
      "level": 2,
      "parentId": "EISEI_004",
      "title": "医の倫理と歯科医師のプロフェッショナリズム",
      "path": "衛生・公衆衛生・医療管理＞必修の基本的事項＞医の倫理と歯科医師のプロフェッショナリズム",
      "order": 1,
      "synonyms": "",
      "keywords": "インフォームドコンセント/守秘義務",
      "priority": 1,
      "source": "ANSWER 2023 vol.4"
    },
    {
      "id": "EISEI_004_02",
      "subject": "衛生・公衆衛生・医療管理",
      "level": 2,
      "parentId": "EISEI_004",
      "title": "社会と歯科医療",
      "path": "衛生・公衆衛生・医療管理＞必修の基本的事項＞社会と歯科医療",
      "order": 2,
      "synonyms": "",
      "keywords": "医療制度",
      "priority": 1,
      "source": "ANSWER 2023 vol.4"
    },
    {
      "id": "EISEI_004_03",
      "subject": "衛生・公衆衛生・医療管理",
      "level": 2,
      "parentId": "EISEI_004",
      "title": "予防と健康管理・増進",
      "path": "衛生・公衆衛生・医療管理＞必修の基本的事項＞予防と健康管理・増進",
      "order": 3,
      "synonyms": "",
      "keywords": "",
      "priority": 1,
      "source": "ANSWER 2023 vol.4"
    },
    {
      "id": "EISEI_004_04",
      "subject": "衛生・公衆衛生・医療管理",
      "level": 2,
      "parentId": "EISEI_004",
      "title": "歯科医療の質と安全の確保",
      "path": "衛生・公衆衛生・医療管理＞必修の基本的事項＞歯科医療の質と安全の確保",
      "order": 4,
      "synonyms": "",
      "keywords": "医療安全/ヒヤリハット",
      "priority": 1,
      "source": "ANSWER 2023 vol.4"
    },
    {
      "id": "EISEI_004_05",
      "subject": "衛生・公衆衛生・医療管理",
      "level": 2,
      "parentId": "EISEI_004",
      "title": "医療面接",
      "path": "衛生・公衆衛生・医療管理＞必修の基本的事項＞医療面接",
      "order": 5,
      "synonyms": "",
      "keywords": "傾聴/共感",
      "priority": 1,
      "source": "ANSWER 2023 vol.4"
    },
    {
      "id": "EISEI_004_06",
      "subject": "衛生・公衆衛生・医療管理",
      "level": 2,
      "parentId": "EISEI_004",
      "title": "臨床判断の基本",
      "path": "衛生・公衆衛生・医療管理＞必修の基本的事項＞臨床判断の基本",
      "order": 6,
      "synonyms": "",
      "keywords": "EBM",
      "priority": 1,
      "source": "ANSWER 2023 vol.4"
    },
    {
      "id": "SHISHU_001",
      "subject": "歯周病学",
      "level": 1,
      "parentId": null,
      "title": "病因",
      "path": "歯周病学＞病因",
      "order": 1,
      "synonyms": "",
      "keywords": "プラーク/歯周病原細菌/咬合性外傷",
      "priority": 2,
      "source": "実践 2020"
    },
    {
      "id": "SHISHU_002",
      "subject": "歯周病学",
      "level": 1,
      "parentId": null,
      "title": "疾患の分類と特徴",
      "path": "歯周病学＞疾患の分類と特徴",
      "order": 2,
      "synonyms": "",
      "keywords": "歯肉炎/歯周炎/壊死性歯周疾患",
      "priority": 2,
      "source": "実践 2020"
    },
    {
      "id": "SHISHU_003",
      "subject": "歯周病学",
      "level": 1,
      "parentId": null,
      "title": "診査、診断",
      "path": "歯周病学＞診査、診断",
      "order": 3,
      "synonyms": "",
      "keywords": "プロービング/X線検査/動揺度",
      "priority": 2,
      "source": "実践 2020"
    },
    {
      "id": "SHISHU_004",
      "subject": "歯周病学",
      "level": 1,
      "parentId": null,
      "title": "歯周基本治療、再評価",
      "path": "歯周病学＞歯周基本治療、再評価",
      "order": 4,
      "synonyms": "",
      "keywords": "スケーリング/SRP/TBI",
      "priority": 2,
      "source": "実践 2020"
    },
    {
      "id": "SHISHU_005",
      "subject": "歯周病学",
      "level": 1,
      "parentId": null,
      "title": "歯周外科治療",
      "path": "歯周病学＞歯周外科治療",
      "order": 5,
      "synonyms": "",
      "keywords": "フラップ手術/GTR/歯周形成手術",
      "priority": 2,
      "source": "実践 2020"
    },
    {
      "id": "SHISHU_006",
      "subject": "歯周病学",
      "level": 1,
      "parentId": null,
      "title": "メインテナンスと口腔機能回復治療",
      "path": "歯周病学＞メインテナンスと口腔機能回復治療",
      "order": 6,
      "synonyms": "",
      "keywords": "SPT/リコール",
      "priority": 2,
      "source": "実践 2020"
    },
    {
      "id": "KISO2_001",
      "subject": "微生物・免疫・薬理・歯科理工",
      "level": 1,
      "parentId": null,
      "title": "微生物学",
      "path": "微生物・免疫・薬理・歯科理工＞微生物学",
      "order": 1,
      "synonyms": "",
      "keywords": "",
      "priority": 2,
      "source": "ANSWER 2023 基礎2"
    },
    {
      "id": "KISO2_001_01",
      "subject": "微生物・免疫・薬理・歯科理工",
      "level": 2,
      "parentId": "KISO2_001",
      "title": "微生物",
      "path": "微生物・免疫・薬理・歯科理工＞微生物学＞微生物",
      "order": 1,
      "synonyms": "",
      "keywords": "細菌/ウイルス/真菌/グラム染色",
      "priority": 2,
      "source": "ANSWER 2023 基礎2"
    },
    {
      "id": "KISO2_001_02",
      "subject": "微生物・免疫・薬理・歯科理工",
      "level": 2,
      "parentId": "KISO2_001",
      "title": "感染（症）",
      "path": "微生物・免疫・薬理・歯科理工＞微生物学＞感染（症）",
      "order": 2,
      "synonyms": "",
      "keywords": "感染経路/日和見感染/院内感染",
      "priority": 2,
      "source": "ANSWER 2023 基礎2"
    },
    {
      "id": "KISO2_001_03",
      "subject": "微生物・免疫・薬理・歯科理工",
      "level": 2,
      "parentId": "KISO2_001",
      "title": "口腔微生物",
      "path": "微生物・免疫・薬理・歯科理工＞微生物学＞口腔微生物",
      "order": 3,
      "synonyms": "",
      "keywords": "Streptococcus mutans/歯周病原細菌",
      "priority": 2,
      "source": "ANSWER 2023 基礎2"
    },
    {
      "id": "KISO2_001_04",
      "subject": "微生物・免疫・薬理・歯科理工",
      "level": 2,
      "parentId": "KISO2_001",
      "title": "滅菌・消毒",
      "path": "微生物・免疫・薬理・歯科理工＞微生物学＞滅菌・消毒",
      "order": 4,
      "synonyms": "",
      "keywords": "オートクレーブ/化学的消毒",
      "priority": 2,
      "source": "ANSWER 2023 基礎2"
    },
    {
      "id": "KISO2_002",
      "subject": "微生物・免疫・薬理・歯科理工",
      "level": 1,
      "parentId": null,
      "title": "免疫学",
      "path": "微生物・免疫・薬理・歯科理工＞免疫学",
      "order": 2,
      "synonyms": "",
      "keywords": "",
      "priority": 2,
      "source": "ANSWER 2023 基礎2"
    },
    {
      "id": "KISO2_002_01",
      "subject": "微生物・免疫・薬理・歯科理工",
      "level": 2,
      "parentId": "KISO2_002",
      "title": "免疫",
      "path": "微生物・免疫・薬理・歯科理工＞免疫学＞免疫",
      "order": 1,
      "synonyms": "",
      "keywords": "自然免疫/獲得免疫/抗体/補体",
      "priority": 2,
      "source": "ANSWER 2023 基礎2"
    },
    {
      "id": "KISO2_002_02",
      "subject": "微生物・免疫・薬理・歯科理工",
      "level": 2,
      "parentId": "KISO2_002",
      "title": "免疫病",
      "path": "微生物・免疫・薬理・歯科理工＞免疫学＞免疫病",
      "order": 2,
      "synonyms": "",
      "keywords": "アレルギー/自己免疫疾患/免疫不全",
      "priority": 2,
      "source": "ANSWER 2023 基礎2"
    },
    {
      "id": "KISO2_003",
      "subject": "微生物・免疫・薬理・歯科理工",
      "level": 1,
      "parentId": null,
      "title": "薬理学",
      "path": "微生物・免疫・薬理・歯科理工＞薬理学",
      "order": 3,
      "synonyms": "",
      "keywords": "",
      "priority": 2,
      "source": "ANSWER 2023 基礎2"
    },
    {
      "id": "KISO2_003_01",
      "subject": "微生物・免疫・薬理・歯科理工",
      "level": 2,
      "parentId": "KISO2_003",
      "title": "薬物動態",
      "path": "微生物・免疫・薬理・歯科理工＞薬理学＞薬物動態",
      "order": 1,
      "synonyms": "",
      "keywords": "吸収/分布/代謝/排泄/半減期",
      "priority": 2,
      "source": "ANSWER 2023 基礎2"
    },
    {
      "id": "KISO2_003_02",
      "subject": "微生物・免疫・薬理・歯科理工",
      "level": 2,
      "parentId": "KISO2_003",
      "title": "薬理作用の発現",
      "path": "微生物・免疫・薬理・歯科理工＞薬理学＞薬理作用の発現",
      "order": 2,
      "synonyms": "",
      "keywords": "受容体/用量反応曲線",
      "priority": 2,
      "source": "ANSWER 2023 基礎2"
    },
    {
      "id": "KISO2_003_03",
      "subject": "微生物・免疫・薬理・歯科理工",
      "level": 2,
      "parentId": "KISO2_003",
      "title": "薬物の併用と副作用",
      "path": "微生物・免疫・薬理・歯科理工＞薬理学＞薬物の併用と副作用",
      "order": 3,
      "synonyms": "",
      "keywords": "相互作用/有害事象",
      "priority": 2,
      "source": "ANSWER 2023 基礎2"
    },
    {
      "id": "KISO2_004",
      "subject": "微生物・免疫・薬理・歯科理工",
      "level": 1,
      "parentId": null,
      "title": "歯科理工学",
      "path": "微生物・免疫・薬理・歯科理工＞歯科理工学",
      "order": 4,
      "synonyms": "理工",
      "keywords": "",
      "priority": 2,
      "source": "ANSWER 2023 基礎2"
    },
    {
      "id": "KISO2_004_01",
      "subject": "微生物・免疫・薬理・歯科理工",
      "level": 2,
      "parentId": "KISO2_004",
      "title": "歯科用材料の物性",
      "path": "微生物・免疫・薬理・歯科理工＞歯科理工学＞歯科用材料の物性",
      "order": 1,
      "synonyms": "",
      "keywords": "機械的性質/熱的性質/生体適合性",
      "priority": 2,
      "source": "ANSWER 2023 基礎2"
    },
    {
      "id": "KISO2_004_02",
      "subject": "微生物・免疫・薬理・歯科理工",
      "level": 2,
      "parentId": "KISO2_004",
      "title": "接着",
      "path": "微生物・免疫・薬理・歯科理工＞歯科理工学＞接着",
      "order": 2,
      "synonyms": "",
      "keywords": "エッチング/ボンディング/接着性レジンセメント",
      "priority": 2,
      "source": "ANSWER 2023 基礎2"
    },
    {
      "id": "KISO2_004_03",
      "subject": "微生物・免疫・薬理・歯科理工",
      "level": 2,
      "parentId": "KISO2_004",
      "title": "各種材料の特性",
      "path": "微生物・免疫・薬理・歯科理工＞歯科理工学＞各種材料の特性",
      "order": 3,
      "synonyms": "",
      "keywords": "コンポジットレジン/セラミックス/金属",
      "priority": 2,
      "source": "ANSWER 2023 基礎2"
    },
    {
      "id": "KISO2_004_04",
      "subject": "微生物・免疫・薬理・歯科理工",
      "level": 2,
      "parentId": "KISO2_004",
      "title": "歯科用器械",
      "path": "微生物・免疫・薬理・歯科理工＞歯科理工学＞歯科用器械",
      "order": 4,
      "synonyms": "",
      "keywords": "切削器具/光重合器",
      "priority": 2,
      "source": "ANSWER 2023 基礎2"
    }
  ]
}